mljet/__init__.py
mljet/cli/__init__.py
mljet/cli/cli.py
mljet/cli/helpers.py
mljet/cli/commands/__init__.py
mljet/cli/commands/build.py
mljet/cli/commands/cook.py
mljet/cli/commands/info/__init__.py
mljet/cli/commands/info/about.py
mljet/cli/commands/info/backends_list.py
mljet/cli/commands/info/frameworks_list.py
mljet/cli/commands/info/strategies_list.py
mljet/cli/commands/info/version.py
mljet/cli/commands/tools/__init__.py
mljet/cli/commands/tools/detect_serializer.py
mljet/contrib/__init__.py
mljet/contrib/analyzer.py
mljet/contrib/dockerutils.py
mljet/contrib/entrypoint.py
mljet/contrib/project_builder.py
mljet/contrib/supported.py
mljet/contrib/validator.py
mljet/contrib/actions/__init__.py
mljet/contrib/actions/docker_build.py
mljet/contrib/actions/project_build.py
mljet/cookie/__init__.py
mljet/cookie/cutter.py
mljet/cookie/validator.py
mljet/cookie/templates/__init__.py
mljet/cookie/templates/backends/__init__.py
mljet/cookie/templates/backends/dispatcher.py
mljet/cookie/templates/backends/_aiohttp/Dockerfile
mljet/cookie/templates/backends/_aiohttp/__init__.py
mljet/cookie/templates/backends/_aiohttp/requirements.txt
mljet/cookie/templates/backends/_aiohttp/server.py
mljet/cookie/templates/backends/_aiohttp/models/model.pkl
mljet/cookie/templates/backends/_fastapi/Dockerfile
mljet/cookie/templates/backends/_fastapi/__init__.py
mljet/cookie/templates/backends/_fastapi/requirements.txt
mljet/cookie/templates/backends/_fastapi/server.py
mljet/cookie/templates/backends/_fastapi/models/model.pkl
mljet/cookie/templates/backends/_flask/Dockerfile
mljet/cookie/templates/backends/_flask/__init__.py
mljet/cookie/templates/backends/_flask/requirements.txt
mljet/cookie/templates/backends/_flask/server.py
mljet/cookie/templates/backends/_flask/models/model.pkl
mljet/cookie/templates/backends/_sanic/Dockerfile
mljet/cookie/templates/backends/_sanic/__init__.py
mljet/cookie/templates/backends/_sanic/requirements.txt
mljet/cookie/templates/backends/_sanic/server.py
mljet-0.7.0.dist-info/entry_points.txt
mljet-0.7.0.dist-info/LICENSE
mljet-0.7.0.dist-info/WHEEL
mljet-0.7.0.dist-info/METADATA
mljet-0.7.0.dist-info/RECORD
